kisskh_downloader/__init__.py
kisskh_downloader/cli.py
kisskh_downloader/downloader.py
kisskh_downloader/enums/__init__.py
kisskh_downloader/enums/quality.py
kisskh_downloader/helper/__init__.py
kisskh_downloader/helper/aes_cipher.py
kisskh_downloader/helper/decrypt_subtitle.py
kisskh_downloader/kisskh_api.py
kisskh_downloader/models/__init__.py
kisskh_downloader/models/drama.py
kisskh_downloader/models/search.py
kisskh_downloader/models/sub.py
kisskh_downloader-0.1.7.dist-info/METADATA
kisskh_downloader-0.1.7.dist-info/WHEEL
kisskh_downloader-0.1.7.dist-info/entry_points.txt
kisskh_downloader-0.1.7.dist-info/RECORD
