Metadata-Version: 2.1
Name: kisskh-downloader
Version: 0.1.7
Summary: Simple downloaded for https://kisskh.co/
Author: Debakar Roy
Author-email: allinonedibakar@gmail.com
Requires-Python: >=3.8,<4.0
Classifier: Programming Language :: Python :: 3
Classifier: Programming Language :: Python :: 3.8
Classifier: Programming Language :: Python :: 3.9
Classifier: Programming Language :: Python :: 3.10
Classifier: Programming Language :: Python :: 3.11
Classifier: Programming Language :: Python :: 3.12
Requires-Dist: click (>=8.1.3,<9.0.0)
Requires-Dist: cryptography (>=41.0.7,<42.0.0)
Requires-Dist: pydantic (>=1.10.5,<2.0.0)
Requires-Dist: pysrt (>=1.1.2,<2.0.0)
Requires-Dist: python-dotenv (>=1.0.0,<2.0.0)
Requires-Dist: requests (>=2.28.2,<3.0.0)
Requires-Dist: validators (>=0.20.0,<0.21.0)
Requires-Dist: yt-dlp (>=2023.2.17,<2024.0.0)
